{
	"hosting": {
		"amplifyhosting": {
			"service": "amplifyhosting",
			"type": "cicd"
		}
	},
	"auth": {
		"booziir6db75974": {
			"service": "Cognito",
			"providerPlugin": "awscloudformation",
			"dependsOn": []
		}
	},
	"api": {
		"booziir": {
			"service": "AppSync",
			"providerPlugin": "awscloudformation",
			"output": {
				"authConfig": {
					"additionalAuthenticationProviders": [],
					"defaultAuthentication": {
						"authenticationType": "AMAZON_COGNITO_USER_POOLS",
						"userPoolConfig": {
							"userPoolId": "authbooziir6db75974"
						}
					}
				}
			}
		}
	},
	"function": {
		"checkCocktailIngredients": {
			"build": true,
			"providerPlugin": "awscloudformation",
			"service": "Lambda",
			"dependsOn": []
		}
	}
}